maleo/toolkit/iamging/__init__.py
maleo/toolkit/iamging/converter.py
maleo/toolkit/iamging/detection.py
maleo/toolkit/iamging/enums.py
maleo/toolkit/iamging/processor.py
maleo/toolkit/iamging/reader.py
maleo_toolkit_imaging-0.0.7.dist-info/licenses/LICENSE
maleo_toolkit_imaging-0.0.7.dist-info/METADATA
maleo_toolkit_imaging-0.0.7.dist-info/WHEEL
maleo_toolkit_imaging-0.0.7.dist-info/top_level.txt
maleo_toolkit_imaging-0.0.7.dist-info/RECORD
