Metadata-Version: 2.4
Name: maleo-toolkit-imaging
Version: 0.0.7
Summary: Imaging toolkit package for MaleoSuite
Author-email: Agra Bima Yuda <agra@nexmedis.com>
License: Proprietary
Requires-Python: >=3.12
License-File: LICENSE
Requires-Dist: black>=25.1.0
Requires-Dist: cfgv>=3.4.0
Requires-Dist: click>=8.2.1
Requires-Dist: distlib>=0.4.0
Requires-Dist: filelock>=3.19.1
Requires-Dist: fsspec>=2025.9.0
Requires-Dist: identify>=2.6.13
Requires-Dist: Jinja2>=3.1.6
Requires-Dist: joblib>=1.5.2
Requires-Dist: llvmlite>=0.45.0
Requires-Dist: maleo-types>=0.0.5
Requires-Dist: MarkupSafe>=3.0.2
Requires-Dist: mpmath>=1.3.0
Requires-Dist: mypy_extensions>=1.1.0
Requires-Dist: networkx>=3.5
Requires-Dist: nodeenv>=1.9.1
Requires-Dist: numpy>=2.3.2
Requires-Dist: packaging>=25.0
Requires-Dist: pathspec>=0.12.1
Requires-Dist: pillow>=11.3.0
Requires-Dist: platformdirs>=4.4.0
Requires-Dist: pre_commit>=4.3.0
Requires-Dist: pydicom>=3.0.1
Requires-Dist: python-dateutil>=2.9.0.post0
Requires-Dist: pytz>=2025.2
Requires-Dist: PyYAML>=6.0.2
Requires-Dist: scipy>=1.16.2
Requires-Dist: setuptools>=80.9.0
Requires-Dist: six>=1.17.0
Requires-Dist: sympy>=1.14.0
Requires-Dist: threadpoolctl>=3.6.0
Requires-Dist: torch>=2.8.0
Requires-Dist: typing_extensions>=4.15.0
Requires-Dist: tzdata>=2025.2
Requires-Dist: virtualenv>=20.34.0
Dynamic: license-file
